{"metadata":{"timestamp":"2025-06-24T12:54:53Z"},"serialNumber":"urn:uuid:4b1ff341-96d8-45c1-995a-26e4af658ea1","components":[{"version":"24.354.13337~0fc7009","name":"luci-app-shadowsocks-rust","type":"application","licenses":[{"license":{"name":"Apache-2.0"}}]},{"type":"application","version":"24.354.13337~0fc7009","name":"luci-i18n-shadowsocks-rust-ar","licenses":[{"license":{"name":"Apache-2.0"}}]},{"type":"application","version":"24.354.13337~0fc7009","name":"luci-i18n-shadowsocks-rust-bg","licenses":[{"license":{"name":"Apache-2.0"}}]},{"licenses":[{"license":{"name":"Apache-2.0"}}],"type":"application","version":"24.354.13337~0fc7009","name":"luci-i18n-shadowsocks-rust-bn"},{"type":"application","version":"24.354.13337~0fc7009","name":"luci-i18n-shadowsocks-rust-ca","licenses":[{"license":{"name":"Apache-2.0"}}]},{"licenses":[{"license":{"name":"Apache-2.0"}}],"type":"application","version":"24.354.13337~0fc7009","name":"luci-i18n-shadowsocks-rust-cs"},{"type":"application","version":"24.354.13337~0fc7009","name":"luci-i18n-shadowsocks-rust-da","licenses":[{"license":{"name":"Apache-2.0"}}]},{"name":"luci-i18n-shadowsocks-rust-de","version":"24.354.13337~0fc7009","type":"application","licenses":[{"license":{"name":"Apache-2.0"}}]},{"licenses":[{"license":{"name":"Apache-2.0"}}],"type":"application","name":"luci-i18n-shadowsocks-rust-el","version":"24.354.13337~0fc7009"},{"version":"24.354.13337~0fc7009","name":"luci-i18n-shadowsocks-rust-es","type":"application","licenses":[{"license":{"name":"Apache-2.0"}}]},{"licenses":[{"license":{"name":"Apache-2.0"}}],"type":"application","version":"24.354.13337~0fc7009","name":"luci-i18n-shadowsocks-rust-fi"},{"licenses":[{"license":{"name":"Apache-2.0"}}],"version":"24.354.13337~0fc7009","name":"luci-i18n-shadowsocks-rust-fr","type":"application"},{"type":"application","name":"luci-i18n-shadowsocks-rust-he","version":"24.354.13337~0fc7009","licenses":[{"license":{"name":"Apache-2.0"}}]},{"type":"application","name":"luci-i18n-shadowsocks-rust-hi","version":"24.354.13337~0fc7009","licenses":[{"license":{"name":"Apache-2.0"}}]},{"licenses":[{"license":{"name":"Apache-2.0"}}],"type":"application","version":"24.354.13337~0fc7009","name":"luci-i18n-shadowsocks-rust-hu"},{"type":"application","version":"24.354.13337~0fc7009","name":"luci-i18n-shadowsocks-rust-it","licenses":[{"license":{"name":"Apache-2.0"}}]},{"licenses":[{"license":{"name":"Apache-2.0"}}],"version":"24.354.13337~0fc7009","name":"luci-i18n-shadowsocks-rust-ja","type":"application"},{"licenses":[{"license":{"name":"Apache-2.0"}}],"name":"luci-i18n-shadowsocks-rust-ko","version":"24.354.13337~0fc7009","type":"application"},{"licenses":[{"license":{"name":"Apache-2.0"}}],"name":"luci-i18n-shadowsocks-rust-lt","version":"24.354.13337~0fc7009","type":"application"},{"licenses":[{"license":{"name":"Apache-2.0"}}],"type":"application","version":"24.354.13337~0fc7009","name":"luci-i18n-shadowsocks-rust-mr"},{"type":"application","version":"24.354.13337~0fc7009","name":"luci-i18n-shadowsocks-rust-ms","licenses":[{"license":{"name":"Apache-2.0"}}]},{"licenses":[{"license":{"name":"Apache-2.0"}}],"name":"luci-i18n-shadowsocks-rust-nl","version":"24.354.13337~0fc7009","type":"application"},{"licenses":[{"license":{"name":"Apache-2.0"}}],"name":"luci-i18n-shadowsocks-rust-no","version":"24.354.13337~0fc7009","type":"application"},{"licenses":[{"license":{"name":"Apache-2.0"}}],"type":"application","name":"luci-i18n-shadowsocks-rust-pl","version":"24.354.13337~0fc7009"},{"licenses":[{"license":{"name":"Apache-2.0"}}],"version":"24.354.13337~0fc7009","name":"luci-i18n-shadowsocks-rust-pt","type":"application"},{"licenses":[{"license":{"name":"Apache-2.0"}}],"type":"application","version":"24.354.13337~0fc7009","name":"luci-i18n-shadowsocks-rust-pt-br"},{"type":"application","name":"luci-i18n-shadowsocks-rust-ro","version":"24.354.13337~0fc7009","licenses":[{"license":{"name":"Apache-2.0"}}]},{"licenses":[{"license":{"name":"Apache-2.0"}}],"type":"application","name":"luci-i18n-shadowsocks-rust-ru","version":"24.354.13337~0fc7009"},{"name":"luci-i18n-shadowsocks-rust-sk","version":"24.354.13337~0fc7009","type":"application","licenses":[{"license":{"name":"Apache-2.0"}}]},{"type":"application","name":"luci-i18n-shadowsocks-rust-sv","version":"24.354.13337~0fc7009","licenses":[{"license":{"name":"Apache-2.0"}}]},{"type":"application","version":"24.354.13337~0fc7009","name":"luci-i18n-shadowsocks-rust-tr","licenses":[{"license":{"name":"Apache-2.0"}}]},{"licenses":[{"license":{"name":"Apache-2.0"}}],"type":"application","name":"luci-i18n-shadowsocks-rust-uk","version":"24.354.13337~0fc7009"},{"licenses":[{"license":{"name":"Apache-2.0"}}],"type":"application","version":"24.354.13337~0fc7009","name":"luci-i18n-shadowsocks-rust-vi"},{"type":"application","name":"luci-i18n-shadowsocks-rust-zh-cn","version":"24.354.13337~0fc7009","licenses":[{"license":{"name":"Apache-2.0"}}]},{"licenses":[{"license":{"name":"Apache-2.0"}}],"version":"24.354.13337~0fc7009","name":"luci-i18n-shadowsocks-rust-zh-tw","type":"application"},{"licenses":[{"license":{"name":"MIT"}}],"name":"shadowsocks-rust-config","version":"1.22.0","type":"application"},{"type":"application","version":"1.22.0","name":"shadowsocks-rust-sslocal","licenses":[{"license":{"name":"MIT"}}]},{"licenses":[{"license":{"name":"MIT"}}],"type":"application","version":"1.22.0","name":"shadowsocks-rust-ssmanager"},{"licenses":[{"license":{"name":"MIT"}}],"version":"1.22.0","name":"shadowsocks-rust-ssserver","type":"application"},{"licenses":[{"license":{"name":"MIT"}}],"type":"application","name":"shadowsocks-rust-ssservice","version":"1.22.0"},{"name":"shadowsocks-rust-ssurl","version":"1.22.0","type":"application","licenses":[{"license":{"name":"MIT"}}]}],"specVersion":"1.4","bomFormat":"CycloneDX","version":1}