{"components":[{"type":"application","name":"einat-ebpf","licenses":[{"license":{"name":"GPL-2.0-or-later"}},{"license":{"name":"GPL-2.0-only"}}],"version":"0.1.8"},{"type":"application","licenses":[{"license":{"name":"MIT"}}],"version":"git-25.087.04343-82838e7","name":"luci-app-einat"},{"licenses":[{"license":{"name":"MIT"}}],"name":"luci-i18n-einat-zh-cn","version":"git-25.087.04343-82838e7","type":"application"},{"type":"application","licenses":[{"license":{"name":"MIT"}}],"version":"git-25.087.04343-82838e7","name":"luci-i18n-einat-zh-tw"}],"bomFormat":"CycloneDX","metadata":{"timestamp":"2025-07-15T03:08:13Z"},"serialNumber":"urn:uuid:df87b89a-1a1d-489d-8350-8f936f5c5a49","version":1,"specVersion":"1.4"}